cloudshell/__init__.py
cloudshell/snmp/__init__.py
cloudshell/snmp/autoload/__init__.py
cloudshell/snmp/autoload/generic_snmp_autoload.py
cloudshell/snmp/autoload/constants/__init__.py
cloudshell/snmp/autoload/constants/entity_constants.py
cloudshell/snmp/autoload/constants/port_constants.py
cloudshell/snmp/autoload/constants/snmpv_v2_constants.py
cloudshell/snmp/autoload/exceptions/__init__.py
cloudshell/snmp/autoload/exceptions/snmp_autoload_error.py
cloudshell/snmp/autoload/helper/__init__.py
cloudshell/snmp/autoload/helper/entity_helper.py
cloudshell/snmp/autoload/helper/module_helper.py
cloudshell/snmp/autoload/helper/port_helper.py
cloudshell/snmp/autoload/helper/port_name_helper.py
cloudshell/snmp/autoload/helper/port_parent_validator.py
cloudshell/snmp/autoload/helper/snmp_autoload_helper.py
cloudshell/snmp/autoload/helper/types/__init__.py
cloudshell/snmp/autoload/helper/types/resource_model.py
cloudshell/snmp/autoload/services/__init__.py
cloudshell/snmp/autoload/services/physical_entities_table.py
cloudshell/snmp/autoload/services/port_mapping_table.py
cloudshell/snmp/autoload/services/port_table.py
cloudshell/snmp/autoload/services/system_info_table.py
cloudshell/snmp/autoload/snmp/__init__.py
cloudshell/snmp/autoload/snmp/snmpv2_data.py
cloudshell/snmp/autoload/snmp/entities/__init__.py
cloudshell/snmp/autoload/snmp/entities/snmp_entity_base.py
cloudshell/snmp/autoload/snmp/entities/snmp_if_entity.py
cloudshell/snmp/autoload/snmp/tables/__init__.py
cloudshell/snmp/autoload/snmp/tables/snmp_entity_table.py
cloudshell/snmp/autoload/snmp/tables/snmp_port_mapping_table.py
cloudshell/snmp/autoload/snmp/tables/snmp_ports_table.py
cloudshell/snmp/autoload/snmp/tables/port_attrs_snmp_tables/__init__.py
cloudshell/snmp/autoload/snmp/tables/port_attrs_snmp_tables/snmp_associated_ports.py
cloudshell/snmp/autoload/snmp/tables/port_attrs_snmp_tables/snmp_port_ip_tables.py
cloudshell/snmp/autoload/snmp/tables/port_attrs_snmp_tables/snmp_ports_auto_negotioation.py
cloudshell_snmp_autoload-2.1.0.dist-info/LICENSE
cloudshell_snmp_autoload-2.1.0.dist-info/METADATA
cloudshell_snmp_autoload-2.1.0.dist-info/WHEEL
cloudshell_snmp_autoload-2.1.0.dist-info/top_level.txt
cloudshell_snmp_autoload-2.1.0.dist-info/RECORD
