Metadata-Version: 2.1
Name: cloudshell-snmp-autoload
Version: 2.1.0
Summary: QualiSystems SNMP Autoload Python package
Home-page: http://www.qualisystems.com/
Author: QualiSystems
Author-email: info@qualisystems.com
Requires-Python: ~=3.7
License-File: LICENSE
Requires-Dist: cloudshell-snmp (<6,>=5.0.0)
